my_innodb_checker/__init__.py
my_innodb_checker/cli.py
my_innodb_checker/constants.py
my_innodb_checker/helpers.py
my_innodb_checker/mysqlsh.py
my_innodb_checker-1.0.1.dist-info/LICENSE
my_innodb_checker-1.0.1.dist-info/METADATA
my_innodb_checker-1.0.1.dist-info/WHEEL
my_innodb_checker-1.0.1.dist-info/entry_points.txt
my_innodb_checker-1.0.1.dist-info/RECORD
