Metadata-Version: 2.1
Name: my-innodb-checker
Version: 1.0.1
Summary: Mysql InnoDB cluster monitoring
Author: Arunas Grigalionis
Author-email: arunas.grigalionis@gmail.com
Requires-Python: >=3.9,<4.0
Classifier: Programming Language :: Python :: 3
Classifier: Programming Language :: Python :: 3.9
Classifier: Programming Language :: Python :: 3.10
Classifier: Programming Language :: Python :: 3.11
Classifier: Programming Language :: Python :: 3.12
Requires-Dist: pymysql (>=1.1.1,<2.0.0)
Requires-Dist: sqlalchemy (>=2.0.36,<3.0.0)
Requires-Dist: tabulate (>=0.9.0,<0.10.0)
